curses_playlist/__init__.py
curses_playlist/controller.py
curses_playlist/curses_gui.py
curses_playlist/flask_controller.py
curses_playlist/flask_debug.py
curses_playlist/gui_state.py
curses_playlist/platform_defs.py
curses_playlist/plist.py
curses_playlist/templates/control.html
curses_playlist/tools.py
curses_playlist/video_file.py
curses_playlist/video_store.py
curses_playlist-0.5.2.dist-info/entry_points.txt
curses_playlist-0.5.2.dist-info/LICENSE
curses_playlist-0.5.2.dist-info/WHEEL
curses_playlist-0.5.2.dist-info/METADATA
curses_playlist-0.5.2.dist-info/RECORD
