Metadata-Version: 2.1
Name: curses-playlist
Version: 0.5.2
Summary: curses based interactive playlist creation for videos
License: MIT
Author: Dr. Dosn
Author-email: dr.dosn@gmail.com
Requires-Python: >=3.7,<4.0
Classifier: License :: OSI Approved :: MIT License
Classifier: Programming Language :: Python :: 3
Classifier: Programming Language :: Python :: 3.10
Classifier: Programming Language :: Python :: 3.7
Classifier: Programming Language :: Python :: 3.8
Classifier: Programming Language :: Python :: 3.9
Requires-Dist: Flask (>=2.2.5,<3.0.0)
Requires-Dist: click (>=8.1.3,<9.0.0)
Requires-Dist: moviepy (>=1.0.3,<2.0.0)
Requires-Dist: pycaw (>=20220416,<20220417)
Requires-Dist: pydantic (>=1.9.1,<2.0.0)
Requires-Dist: requests (<3.0.0)
Requires-Dist: windows-curses (>=2.3.0,<3.0.0)
